offline_listens/__init__.py
offline_listens/__main__.py
offline_listens/listens.py
offline_listens/parse.py
offline_listens/py.typed
offline_listens-0.1.0.dist-info/licenses/LICENSE
offline_listens-0.1.0.dist-info/METADATA
offline_listens-0.1.0.dist-info/WHEEL
offline_listens-0.1.0.dist-info/entry_points.txt
offline_listens-0.1.0.dist-info/top_level.txt
offline_listens-0.1.0.dist-info/RECORD
