Metadata-Version: 2.4
Name: offline_listens
Version: 0.1.0
Summary: an offline listening history
Author: purarue
License-Expression: MIT
Project-URL: Homepage, https://github.com/purarue/offline_listens
Keywords: music
Classifier: Programming Language :: Python
Classifier: Programming Language :: Python :: 3
Classifier: Programming Language :: Python :: 3 :: Only
Classifier: Programming Language :: Python :: 3.10
Classifier: Programming Language :: Python :: 3.11
Classifier: Programming Language :: Python :: 3.12
Classifier: Programming Language :: Python :: 3.13
Requires-Python: >=3.10
License-File: LICENSE
Requires-Dist: autotui
Requires-Dist: click>=8.0
Requires-Dist: logzero
Requires-Dist: pyfzf-iter
Requires-Dist: pyyaml
Requires-Dist: simplejson
Provides-Extra: testing
Requires-Dist: flake8; extra == "testing"
Requires-Dist: mypy; extra == "testing"
Requires-Dist: types-simplejson; extra == "testing"
Dynamic: license-file
